scom7330/__init__.py
scom7330/audiolib.py
scom7330/audiolib_tool.py
scom7330/config/message.py
scom7330/config.py
scom7330/temp.py
scom7330/temp.txt
scom7330-0.1.1.dist-info/entry_points.txt
scom7330-0.1.1.dist-info/LICENSE
scom7330-0.1.1.dist-info/WHEEL
scom7330-0.1.1.dist-info/METADATA
scom7330-0.1.1.dist-info/RECORD
