Metadata-Version: 2.1
Name: scom7330
Version: 0.1.1
Summary: A tool to manipulate various data, including Audio Libraries (ex CustomAudioLib.bin) for the SCOM 7330 repeater
Home-page: https://github.com/ad1217/python-SCOM7330
License: MIT
Keywords: ham-radio,hamradio,scom,scom-7330
Author: Adam Goldsmith
Author-email: adam@adamgoldsmith.name
Requires-Python: >=3.8,<4.0
Classifier: Environment :: Console
Classifier: License :: OSI Approved :: MIT License
Classifier: Programming Language :: Python :: 3
Classifier: Programming Language :: Python :: 3.8
Classifier: Programming Language :: Python :: 3.9
Classifier: Topic :: Communications :: Ham Radio
Classifier: Topic :: Utilities
Classifier: Typing :: Typed
Project-URL: Repository, https://github.com/ad1217/python-SCOM7330
